korail2/__init__.py
korail2/constants.py
korail2/korail2.py
korail2-0.2.6.dist-info/DESCRIPTION.rst
korail2-0.2.6.dist-info/METADATA
korail2-0.2.6.dist-info/RECORD
korail2-0.2.6.dist-info/WHEEL
korail2-0.2.6.dist-info/metadata.json
korail2-0.2.6.dist-info/top_level.txt
